rstdiff/__init__.py
rstdiff/treediff/__init__.py
rstdiff-0.5.2.dist-info/LICENSE.rst
rstdiff-0.5.2.dist-info/METADATA
rstdiff-0.5.2.dist-info/WHEEL
rstdiff-0.5.2.dist-info/entry_points.txt
rstdiff-0.5.2.dist-info/top_level.txt
rstdiff-0.5.2.dist-info/RECORD
