Metadata-Version: 2.1
Name: rstdiff
Version: 0.5.2
Summary: Creates a diff highlighting changes between two reStructuredText inputs
Home-page: https://github.com/SamWilsn/rstdiff
Author: Stefan Merten
Author-email: smerten@oekonux.de
License: GPL 2+
Classifier: Programming Language :: Python :: 3
Classifier: License :: OSI Approved :: GNU General Public License v2 or later (GPLv2+)
License-File: LICENSE.rst
Requires-Dist: docutils
Requires-Dist: Pygments
